{"nodes": [{"id": "d_padhai_style_sync_ai_dossier_md", "label": "DOSSIER.md", "file_type": "document", "source_file": "D:\\Padhai\\Style-Sync-AI\\DOSSIER.md", "source_location": "L1"}, {"id": "style_sync_ai_dossier_stylesync_ai_complete_project_dossier", "label": "StyleSync AI \u2014 Complete Project Dossier", "file_type": "document", "source_file": "D:\\Padhai\\Style-Sync-AI\\DOSSIER.md", "source_location": "L1"}, {"id": "style_sync_ai_dossier_0_read_this_first_documented_vs_built", "label": "\u00a70. READ THIS FIRST \u2014 \"Documented\" vs \"Built\"", "file_type": "document", "source_file": "D:\\Padhai\\Style-Sync-AI\\DOSSIER.md", "source_location": "L9"}, {"id": "style_sync_ai_dossier_1_executive_summary", "label": "1. Executive Summary", "file_type": "document", "source_file": "D:\\Padhai\\Style-Sync-AI\\DOSSIER.md", "source_location": "L28"}, {"id": "style_sync_ai_dossier_2_system_architecture", "label": "2. System Architecture", "file_type": "document", "source_file": "D:\\Padhai\\Style-Sync-AI\\DOSSIER.md", "source_location": "L48"}, {"id": "style_sync_ai_dossier_user_flow", "label": "User Flow", "file_type": "document", "source_file": "D:\\Padhai\\Style-Sync-AI\\DOSSIER.md", "source_location": "L50"}, {"id": "style_sync_ai_dossier_frontend_architecture", "label": "Frontend Architecture", "file_type": "document", "source_file": "D:\\Padhai\\Style-Sync-AI\\DOSSIER.md", "source_location": "L62"}, {"id": "style_sync_ai_dossier_backend_architecture", "label": "Backend Architecture", "file_type": "document", "source_file": "D:\\Padhai\\Style-Sync-AI\\DOSSIER.md", "source_location": "L68"}, {"id": "style_sync_ai_dossier_database_architecture", "label": "Database Architecture", "file_type": "document", "source_file": "D:\\Padhai\\Style-Sync-AI\\DOSSIER.md", "source_location": "L72"}, {"id": "style_sync_ai_dossier_authentication_flow", "label": "Authentication Flow", "file_type": "document", "source_file": "D:\\Padhai\\Style-Sync-AI\\DOSSIER.md", "source_location": "L76"}, {"id": "style_sync_ai_dossier_api_flow_representative_upload", "label": "API Flow (representative \u2014 upload)", "file_type": "document", "source_file": "D:\\Padhai\\Style-Sync-AI\\DOSSIER.md", "source_location": "L79"}, {"id": "style_sync_ai_dossier_data_flow", "label": "Data Flow", "file_type": "document", "source_file": "D:\\Padhai\\Style-Sync-AI\\DOSSIER.md", "source_location": "L82"}, {"id": "style_sync_ai_dossier_storage_layer", "label": "Storage Layer", "file_type": "document", "source_file": "D:\\Padhai\\Style-Sync-AI\\DOSSIER.md", "source_location": "L85"}, {"id": "style_sync_ai_dossier_deployment_architecture", "label": "Deployment Architecture", "file_type": "document", "source_file": "D:\\Padhai\\Style-Sync-AI\\DOSSIER.md", "source_location": "L89"}, {"id": "style_sync_ai_dossier_external_services_used", "label": "External Services Used", "file_type": "document", "source_file": "D:\\Padhai\\Style-Sync-AI\\DOSSIER.md", "source_location": "L92"}, {"id": "style_sync_ai_dossier_architecture_diagram_ascii", "label": "Architecture Diagram (ASCII)", "file_type": "document", "source_file": "D:\\Padhai\\Style-Sync-AI\\DOSSIER.md", "source_location": "L95"}, {"id": "style_sync_ai_dossier_component_interaction_diagram_upload_recommend", "label": "Component Interaction Diagram (upload \u2192 recommend)", "file_type": "document", "source_file": "D:\\Padhai\\Style-Sync-AI\\DOSSIER.md", "source_location": "L121"}, {"id": "style_sync_ai_dossier_3_frontend_deep_dive", "label": "3. Frontend Deep Dive", "file_type": "document", "source_file": "D:\\Padhai\\Style-Sync-AI\\DOSSIER.md", "source_location": "L138"}, {"id": "style_sync_ai_dossier_next_js_16_app_router", "label": "Next.js 16 (App Router)", "file_type": "document", "source_file": "D:\\Padhai\\Style-Sync-AI\\DOSSIER.md", "source_location": "L140"}, {"id": "style_sync_ai_dossier_react_19", "label": "React 19", "file_type": "document", "source_file": "D:\\Padhai\\Style-Sync-AI\\DOSSIER.md", "source_location": "L147"}, {"id": "style_sync_ai_dossier_state_management", "label": "State Management", "file_type": "document", "source_file": "D:\\Padhai\\Style-Sync-AI\\DOSSIER.md", "source_location": "L152"}, {"id": "style_sync_ai_dossier_routing", "label": "Routing", "file_type": "document", "source_file": "D:\\Padhai\\Style-Sync-AI\\DOSSIER.md", "source_location": "L157"}, {"id": "style_sync_ai_dossier_forms", "label": "Forms", "file_type": "document", "source_file": "D:\\Padhai\\Style-Sync-AI\\DOSSIER.md", "source_location": "L160"}, {"id": "style_sync_ai_dossier_ui_libraries", "label": "UI Libraries", "file_type": "document", "source_file": "D:\\Padhai\\Style-Sync-AI\\DOSSIER.md", "source_location": "L163"}, {"id": "style_sync_ai_dossier_styling", "label": "Styling", "file_type": "document", "source_file": "D:\\Padhai\\Style-Sync-AI\\DOSSIER.md", "source_location": "L167"}, {"id": "style_sync_ai_dossier_performance_optimization", "label": "Performance Optimization", "file_type": "document", "source_file": "D:\\Padhai\\Style-Sync-AI\\DOSSIER.md", "source_location": "L170"}, {"id": "style_sync_ai_dossier_error_handling", "label": "Error Handling", "file_type": "document", "source_file": "D:\\Padhai\\Style-Sync-AI\\DOSSIER.md", "source_location": "L173"}, {"id": "style_sync_ai_dossier_caching", "label": "Caching", "file_type": "document", "source_file": "D:\\Padhai\\Style-Sync-AI\\DOSSIER.md", "source_location": "L176"}, {"id": "style_sync_ai_dossier_accessibility", "label": "Accessibility", "file_type": "document", "source_file": "D:\\Padhai\\Style-Sync-AI\\DOSSIER.md", "source_location": "L179"}, {"id": "style_sync_ai_dossier_responsive_design", "label": "Responsive Design", "file_type": "document", "source_file": "D:\\Padhai\\Style-Sync-AI\\DOSSIER.md", "source_location": "L182"}, {"id": "style_sync_ai_dossier_4_backend_deep_dive", "label": "4. Backend Deep Dive", "file_type": "document", "source_file": "D:\\Padhai\\Style-Sync-AI\\DOSSIER.md", "source_location": "L187"}, {"id": "style_sync_ai_dossier_apis_next_js_route_handlers", "label": "APIs \u2014 Next.js Route Handlers", "file_type": "document", "source_file": "D:\\Padhai\\Style-Sync-AI\\DOSSIER.md", "source_location": "L189"}, {"id": "style_sync_ai_dossier_service_framework_style_sync_backend_workspace_package", "label": "Service Framework \u2014 `@style-sync/backend` workspace package", "file_type": "document", "source_file": "D:\\Padhai\\Style-Sync-AI\\DOSSIER.md", "source_location": "L196"}, {"id": "style_sync_ai_dossier_authentication_clerk", "label": "Authentication \u2014 Clerk", "file_type": "document", "source_file": "D:\\Padhai\\Style-Sync-AI\\DOSSIER.md", "source_location": "L201"}, {"id": "style_sync_ai_dossier_authorization", "label": "Authorization", "file_type": "document", "source_file": "D:\\Padhai\\Style-Sync-AI\\DOSSIER.md", "source_location": "L207"}, {"id": "style_sync_ai_dossier_middleware", "label": "Middleware", "file_type": "document", "source_file": "D:\\Padhai\\Style-Sync-AI\\DOSSIER.md", "source_location": "L210"}, {"id": "style_sync_ai_dossier_logging", "label": "Logging", "file_type": "document", "source_file": "D:\\Padhai\\Style-Sync-AI\\DOSSIER.md", "source_location": "L213"}, {"id": "style_sync_ai_dossier_error_handling_216", "label": "Error Handling", "file_type": "document", "source_file": "D:\\Padhai\\Style-Sync-AI\\DOSSIER.md", "source_location": "L216"}, {"id": "style_sync_ai_dossier_rate_limiting", "label": "Rate Limiting", "file_type": "document", "source_file": "D:\\Padhai\\Style-Sync-AI\\DOSSIER.md", "source_location": "L219"}, {"id": "style_sync_ai_dossier_validation", "label": "Validation", "file_type": "document", "source_file": "D:\\Padhai\\Style-Sync-AI\\DOSSIER.md", "source_location": "L223"}, {"id": "style_sync_ai_dossier_background_jobs", "label": "Background Jobs", "file_type": "document", "source_file": "D:\\Padhai\\Style-Sync-AI\\DOSSIER.md", "source_location": "L226"}, {"id": "style_sync_ai_dossier_caching_message_queues_websockets", "label": "Caching / Message Queues / WebSockets", "file_type": "document", "source_file": "D:\\Padhai\\Style-Sync-AI\\DOSSIER.md", "source_location": "L229"}, {"id": "style_sync_ai_dossier_5_database_deep_dive", "label": "5. Database Deep Dive", "file_type": "document", "source_file": "D:\\Padhai\\Style-Sync-AI\\DOSSIER.md", "source_location": "L234"}, {"id": "style_sync_ai_dossier_database_choice_postgresql_prisma_7", "label": "Database choice \u2014 PostgreSQL + Prisma 7", "file_type": "document", "source_file": "D:\\Padhai\\Style-Sync-AI\\DOSSIER.md", "source_location": "L236"}, {"id": "style_sync_ai_dossier_schema_design_models", "label": "Schema Design (models)", "file_type": "document", "source_file": "D:\\Padhai\\Style-Sync-AI\\DOSSIER.md", "source_location": "L240"}, {"id": "style_sync_ai_dossier_relationships", "label": "Relationships", "file_type": "document", "source_file": "D:\\Padhai\\Style-Sync-AI\\DOSSIER.md", "source_location": "L243"}, {"id": "style_sync_ai_dossier_indexing", "label": "Indexing", "file_type": "document", "source_file": "D:\\Padhai\\Style-Sync-AI\\DOSSIER.md", "source_location": "L249"}, {"id": "style_sync_ai_dossier_query_optimization", "label": "Query Optimization", "file_type": "document", "source_file": "D:\\Padhai\\Style-Sync-AI\\DOSSIER.md", "source_location": "L252"}, {"id": "style_sync_ai_dossier_scaling_strategy", "label": "Scaling Strategy", "file_type": "document", "source_file": "D:\\Padhai\\Style-Sync-AI\\DOSSIER.md", "source_location": "L255"}, {"id": "style_sync_ai_dossier_backup_consistency_transactions", "label": "Backup / Consistency / Transactions", "file_type": "document", "source_file": "D:\\Padhai\\Style-Sync-AI\\DOSSIER.md", "source_location": "L258"}, {"id": "style_sync_ai_dossier_er_diagram", "label": "ER Diagram", "file_type": "document", "source_file": "D:\\Padhai\\Style-Sync-AI\\DOSSIER.md", "source_location": "L261"}, {"id": "style_sync_ai_dossier_sample_tables", "label": "Sample Tables", "file_type": "document", "source_file": "D:\\Padhai\\Style-Sync-AI\\DOSSIER.md", "source_location": "L276"}, {"id": "style_sync_ai_dossier_common_queries", "label": "Common Queries", "file_type": "document", "source_file": "D:\\Padhai\\Style-Sync-AI\\DOSSIER.md", "source_location": "L289"}, {"id": "style_sync_ai_dossier_6_technology_breakdown", "label": "6. Technology Breakdown", "file_type": "document", "source_file": "D:\\Padhai\\Style-Sync-AI\\DOSSIER.md", "source_location": "L303"}, {"id": "style_sync_ai_dossier_7_feature_by_feature_analysis", "label": "7. Feature-by-Feature Analysis", "file_type": "document", "source_file": "D:\\Padhai\\Style-Sync-AI\\DOSSIER.md", "source_location": "L325"}, {"id": "style_sync_ai_dossier_a_garment_upload_ai_classification", "label": "A. Garment Upload + AI Classification", "file_type": "document", "source_file": "D:\\Padhai\\Style-Sync-AI\\DOSSIER.md", "source_location": "L327"}, {"id": "style_sync_ai_dossier_b_ai_outfit_generation", "label": "B. AI Outfit Generation", "file_type": "document", "source_file": "D:\\Padhai\\Style-Sync-AI\\DOSSIER.md", "source_location": "L335"}, {"id": "style_sync_ai_dossier_c_weather_occasion_recommendation_engine_the_crown_jewel", "label": "C. Weather + Occasion Recommendation Engine (the crown jewel)", "file_type": "document", "source_file": "D:\\Padhai\\Style-Sync-AI\\DOSSIER.md", "source_location": "L342"}, {"id": "style_sync_ai_dossier_d_preference_learning_closed_loop", "label": "D. Preference Learning (closed loop)", "file_type": "document", "source_file": "D:\\Padhai\\Style-Sync-AI\\DOSSIER.md", "source_location": "L354"}, {"id": "style_sync_ai_dossier_e_weekly_planner_wear_history_insights", "label": "E. Weekly Planner / Wear History / Insights", "file_type": "document", "source_file": "D:\\Padhai\\Style-Sync-AI\\DOSSIER.md", "source_location": "L360"}, {"id": "style_sync_ai_dossier_8_security_analysis", "label": "8. Security Analysis", "file_type": "document", "source_file": "D:\\Padhai\\Style-Sync-AI\\DOSSIER.md", "source_location": "L367"}, {"id": "style_sync_ai_dossier_9_scalability_discussion", "label": "9. Scalability Discussion", "file_type": "document", "source_file": "D:\\Padhai\\Style-Sync-AI\\DOSSIER.md", "source_location": "L390"}, {"id": "style_sync_ai_dossier_10_deployment_devops", "label": "10. Deployment & DevOps", "file_type": "document", "source_file": "D:\\Padhai\\Style-Sync-AI\\DOSSIER.md", "source_location": "L411"}, {"id": "style_sync_ai_dossier_11_design_decisions", "label": "11. Design Decisions", "file_type": "document", "source_file": "D:\\Padhai\\Style-Sync-AI\\DOSSIER.md", "source_location": "L428"}, {"id": "style_sync_ai_dossier_12_challenges_problem_solving_10", "label": "12. Challenges & Problem Solving (10)", "file_type": "document", "source_file": "D:\\Padhai\\Style-Sync-AI\\DOSSIER.md", "source_location": "L440"}, {"id": "style_sync_ai_dossier_13_resume_discussion_preparation", "label": "13. Resume Discussion Preparation", "file_type": "document", "source_file": "D:\\Padhai\\Style-Sync-AI\\DOSSIER.md", "source_location": "L455"}, {"id": "style_sync_ai_dossier_tell_me_about_this_project", "label": "Tell me about this project", "file_type": "document", "source_file": "D:\\Padhai\\Style-Sync-AI\\DOSSIER.md", "source_location": "L457"}, {"id": "style_sync_ai_dossier_why_did_you_build_it", "label": "Why did you build it?", "file_type": "document", "source_file": "D:\\Padhai\\Style-Sync-AI\\DOSSIER.md", "source_location": "L462"}, {"id": "style_sync_ai_dossier_what_was_your_contribution", "label": "What was your contribution?", "file_type": "document", "source_file": "D:\\Padhai\\Style-Sync-AI\\DOSSIER.md", "source_location": "L466"}, {"id": "style_sync_ai_dossier_hardest_problem", "label": "Hardest problem?", "file_type": "document", "source_file": "D:\\Padhai\\Style-Sync-AI\\DOSSIER.md", "source_location": "L469"}, {"id": "style_sync_ai_dossier_what_would_you_improve", "label": "What would you improve?", "file_type": "document", "source_file": "D:\\Padhai\\Style-Sync-AI\\DOSSIER.md", "source_location": "L473"}, {"id": "style_sync_ai_dossier_what_did_you_learn", "label": "What did you learn?", "file_type": "document", "source_file": "D:\\Padhai\\Style-Sync-AI\\DOSSIER.md", "source_location": "L476"}, {"id": "style_sync_ai_dossier_14_technical_interview_questions", "label": "14. Technical Interview Questions", "file_type": "document", "source_file": "D:\\Padhai\\Style-Sync-AI\\DOSSIER.md", "source_location": "L481"}, {"id": "style_sync_ai_dossier_beginner_20", "label": "Beginner (20)", "file_type": "document", "source_file": "D:\\Padhai\\Style-Sync-AI\\DOSSIER.md", "source_location": "L483"}, {"id": "style_sync_ai_dossier_intermediate_30", "label": "Intermediate (30)", "file_type": "document", "source_file": "D:\\Padhai\\Style-Sync-AI\\DOSSIER.md", "source_location": "L505"}, {"id": "style_sync_ai_dossier_advanced_30", "label": "Advanced (30)", "file_type": "document", "source_file": "D:\\Padhai\\Style-Sync-AI\\DOSSIER.md", "source_location": "L537"}, {"id": "style_sync_ai_dossier_15_project_defense_round_25_skeptical_questions_answers", "label": "15. Project Defense Round (25 skeptical questions + answers)", "file_type": "document", "source_file": "D:\\Padhai\\Style-Sync-AI\\DOSSIER.md", "source_location": "L571"}, {"id": "style_sync_ai_dossier_16_hidden_follow_up_questions_3_per_key_answer", "label": "16. Hidden Follow-Up Questions (3 per key answer)", "file_type": "document", "source_file": "D:\\Padhai\\Style-Sync-AI\\DOSSIER.md", "source_location": "L601"}, {"id": "style_sync_ai_dossier_17_production_grade_improvements", "label": "17. Production-Grade Improvements", "file_type": "document", "source_file": "D:\\Padhai\\Style-Sync-AI\\DOSSIER.md", "source_location": "L630"}, {"id": "style_sync_ai_dossier_18_complete_viva_preparation_sheet_rapid_revision", "label": "18. Complete Viva Preparation Sheet (rapid revision)", "file_type": "document", "source_file": "D:\\Padhai\\Style-Sync-AI\\DOSSIER.md", "source_location": "L641"}, {"id": "style_sync_ai_dossier_19_knowledge_gaps_and_how_to_prepare", "label": "19. Knowledge Gaps (and how to prepare)", "file_type": "document", "source_file": "D:\\Padhai\\Style-Sync-AI\\DOSSIER.md", "source_location": "L654"}, {"id": "style_sync_ai_dossier_20_interview_readiness_score", "label": "20. Interview Readiness Score", "file_type": "document", "source_file": "D:\\Padhai\\Style-Sync-AI\\DOSSIER.md", "source_location": "L666"}], "edges": [{"source": "d_padhai_style_sync_ai_dossier_md", "target": "style_sync_ai_dossier_stylesync_ai_complete_project_dossier", "relation": "contains", "confidence": "EXTRACTED", "source_file": "D:\\Padhai\\Style-Sync-AI\\DOSSIER.md", "source_location": "L1", "weight": 1.0}, {"source": "style_sync_ai_dossier_stylesync_ai_complete_project_dossier", "target": "style_sync_ai_dossier_0_read_this_first_documented_vs_built", "relation": "contains", "confidence": "EXTRACTED", "source_file": "D:\\Padhai\\Style-Sync-AI\\DOSSIER.md", "source_location": "L9", "weight": 1.0}, {"source": "d_padhai_style_sync_ai_dossier_md", "target": "style_sync_ai_dossier_1_executive_summary", "relation": "contains", "confidence": "EXTRACTED", "source_file": "D:\\Padhai\\Style-Sync-AI\\DOSSIER.md", "source_location": "L28", "weight": 1.0}, {"source": "d_padhai_style_sync_ai_dossier_md", "target": "style_sync_ai_dossier_2_system_architecture", "relation": "contains", "confidence": "EXTRACTED", "source_file": "D:\\Padhai\\Style-Sync-AI\\DOSSIER.md", "source_location": "L48", "weight": 1.0}, {"source": "style_sync_ai_dossier_2_system_architecture", "target": "style_sync_ai_dossier_user_flow", "relation": "contains", "confidence": "EXTRACTED", "source_file": "D:\\Padhai\\Style-Sync-AI\\DOSSIER.md", "source_location": "L50", "weight": 1.0}, {"source": "style_sync_ai_dossier_2_system_architecture", "target": "style_sync_ai_dossier_frontend_architecture", "relation": "contains", "confidence": "EXTRACTED", "source_file": "D:\\Padhai\\Style-Sync-AI\\DOSSIER.md", "source_location": "L62", "weight": 1.0}, {"source": "style_sync_ai_dossier_2_system_architecture", "target": "style_sync_ai_dossier_backend_architecture", "relation": "contains", "confidence": "EXTRACTED", "source_file": "D:\\Padhai\\Style-Sync-AI\\DOSSIER.md", "source_location": "L68", "weight": 1.0}, {"source": "style_sync_ai_dossier_2_system_architecture", "target": "style_sync_ai_dossier_database_architecture", "relation": "contains", "confidence": "EXTRACTED", "source_file": "D:\\Padhai\\Style-Sync-AI\\DOSSIER.md", "source_location": "L72", "weight": 1.0}, {"source": "style_sync_ai_dossier_2_system_architecture", "target": "style_sync_ai_dossier_authentication_flow", "relation": "contains", "confidence": "EXTRACTED", "source_file": "D:\\Padhai\\Style-Sync-AI\\DOSSIER.md", "source_location": "L76", "weight": 1.0}, {"source": "style_sync_ai_dossier_2_system_architecture", "target": "style_sync_ai_dossier_api_flow_representative_upload", "relation": "contains", "confidence": "EXTRACTED", "source_file": "D:\\Padhai\\Style-Sync-AI\\DOSSIER.md", "source_location": "L79", "weight": 1.0}, {"source": "style_sync_ai_dossier_2_system_architecture", "target": "style_sync_ai_dossier_data_flow", "relation": "contains", "confidence": "EXTRACTED", "source_file": "D:\\Padhai\\Style-Sync-AI\\DOSSIER.md", "source_location": "L82", "weight": 1.0}, {"source": "style_sync_ai_dossier_2_system_architecture", "target": "style_sync_ai_dossier_storage_layer", "relation": "contains", "confidence": "EXTRACTED", "source_file": "D:\\Padhai\\Style-Sync-AI\\DOSSIER.md", "source_location": "L85", "weight": 1.0}, {"source": "style_sync_ai_dossier_2_system_architecture", "target": "style_sync_ai_dossier_deployment_architecture", "relation": "contains", "confidence": "EXTRACTED", "source_file": "D:\\Padhai\\Style-Sync-AI\\DOSSIER.md", "source_location": "L89", "weight": 1.0}, {"source": "style_sync_ai_dossier_2_system_architecture", "target": "style_sync_ai_dossier_external_services_used", "relation": "contains", "confidence": "EXTRACTED", "source_file": "D:\\Padhai\\Style-Sync-AI\\DOSSIER.md", "source_location": "L92", "weight": 1.0}, {"source": "style_sync_ai_dossier_2_system_architecture", "target": "style_sync_ai_dossier_architecture_diagram_ascii", "relation": "contains", "confidence": "EXTRACTED", "source_file": "D:\\Padhai\\Style-Sync-AI\\DOSSIER.md", "source_location": "L95", "weight": 1.0}, {"source": "style_sync_ai_dossier_2_system_architecture", "target": "style_sync_ai_dossier_component_interaction_diagram_upload_recommend", "relation": "contains", "confidence": "EXTRACTED", "source_file": "D:\\Padhai\\Style-Sync-AI\\DOSSIER.md", "source_location": "L121", "weight": 1.0}, {"source": "d_padhai_style_sync_ai_dossier_md", "target": "style_sync_ai_dossier_3_frontend_deep_dive", "relation": "contains", "confidence": "EXTRACTED", "source_file": "D:\\Padhai\\Style-Sync-AI\\DOSSIER.md", "source_location": "L138", "weight": 1.0}, {"source": "style_sync_ai_dossier_3_frontend_deep_dive", "target": "style_sync_ai_dossier_next_js_16_app_router", "relation": "contains", "confidence": "EXTRACTED", "source_file": "D:\\Padhai\\Style-Sync-AI\\DOSSIER.md", "source_location": "L140", "weight": 1.0}, {"source": "style_sync_ai_dossier_3_frontend_deep_dive", "target": "style_sync_ai_dossier_react_19", "relation": "contains", "confidence": "EXTRACTED", "source_file": "D:\\Padhai\\Style-Sync-AI\\DOSSIER.md", "source_location": "L147", "weight": 1.0}, {"source": "style_sync_ai_dossier_3_frontend_deep_dive", "target": "style_sync_ai_dossier_state_management", "relation": "contains", "confidence": "EXTRACTED", "source_file": "D:\\Padhai\\Style-Sync-AI\\DOSSIER.md", "source_location": "L152", "weight": 1.0}, {"source": "style_sync_ai_dossier_3_frontend_deep_dive", "target": "style_sync_ai_dossier_routing", "relation": "contains", "confidence": "EXTRACTED", "source_file": "D:\\Padhai\\Style-Sync-AI\\DOSSIER.md", "source_location": "L157", "weight": 1.0}, {"source": "style_sync_ai_dossier_3_frontend_deep_dive", "target": "style_sync_ai_dossier_forms", "relation": "contains", "confidence": "EXTRACTED", "source_file": "D:\\Padhai\\Style-Sync-AI\\DOSSIER.md", "source_location": "L160", "weight": 1.0}, {"source": "style_sync_ai_dossier_3_frontend_deep_dive", "target": "style_sync_ai_dossier_ui_libraries", "relation": "contains", "confidence": "EXTRACTED", "source_file": "D:\\Padhai\\Style-Sync-AI\\DOSSIER.md", "source_location": "L163", "weight": 1.0}, {"source": "style_sync_ai_dossier_3_frontend_deep_dive", "target": "style_sync_ai_dossier_styling", "relation": "contains", "confidence": "EXTRACTED", "source_file": "D:\\Padhai\\Style-Sync-AI\\DOSSIER.md", "source_location": "L167", "weight": 1.0}, {"source": "style_sync_ai_dossier_3_frontend_deep_dive", "target": "style_sync_ai_dossier_performance_optimization", "relation": "contains", "confidence": "EXTRACTED", "source_file": "D:\\Padhai\\Style-Sync-AI\\DOSSIER.md", "source_location": "L170", "weight": 1.0}, {"source": "style_sync_ai_dossier_3_frontend_deep_dive", "target": "style_sync_ai_dossier_error_handling", "relation": "contains", "confidence": "EXTRACTED", "source_file": "D:\\Padhai\\Style-Sync-AI\\DOSSIER.md", "source_location": "L173", "weight": 1.0}, {"source": "style_sync_ai_dossier_3_frontend_deep_dive", "target": "style_sync_ai_dossier_caching", "relation": "contains", "confidence": "EXTRACTED", "source_file": "D:\\Padhai\\Style-Sync-AI\\DOSSIER.md", "source_location": "L176", "weight": 1.0}, {"source": "style_sync_ai_dossier_3_frontend_deep_dive", "target": "style_sync_ai_dossier_accessibility", "relation": "contains", "confidence": "EXTRACTED", "source_file": "D:\\Padhai\\Style-Sync-AI\\DOSSIER.md", "source_location": "L179", "weight": 1.0}, {"source": "style_sync_ai_dossier_3_frontend_deep_dive", "target": "style_sync_ai_dossier_responsive_design", "relation": "contains", "confidence": "EXTRACTED", "source_file": "D:\\Padhai\\Style-Sync-AI\\DOSSIER.md", "source_location": "L182", "weight": 1.0}, {"source": "d_padhai_style_sync_ai_dossier_md", "target": "style_sync_ai_dossier_4_backend_deep_dive", "relation": "contains", "confidence": "EXTRACTED", "source_file": "D:\\Padhai\\Style-Sync-AI\\DOSSIER.md", "source_location": "L187", "weight": 1.0}, {"source": "style_sync_ai_dossier_4_backend_deep_dive", "target": "style_sync_ai_dossier_apis_next_js_route_handlers", "relation": "contains", "confidence": "EXTRACTED", "source_file": "D:\\Padhai\\Style-Sync-AI\\DOSSIER.md", "source_location": "L189", "weight": 1.0}, {"source": "style_sync_ai_dossier_4_backend_deep_dive", "target": "style_sync_ai_dossier_service_framework_style_sync_backend_workspace_package", "relation": "contains", "confidence": "EXTRACTED", "source_file": "D:\\Padhai\\Style-Sync-AI\\DOSSIER.md", "source_location": "L196", "weight": 1.0}, {"source": "style_sync_ai_dossier_4_backend_deep_dive", "target": "style_sync_ai_dossier_authentication_clerk", "relation": "contains", "confidence": "EXTRACTED", "source_file": "D:\\Padhai\\Style-Sync-AI\\DOSSIER.md", "source_location": "L201", "weight": 1.0}, {"source": "style_sync_ai_dossier_4_backend_deep_dive", "target": "style_sync_ai_dossier_authorization", "relation": "contains", "confidence": "EXTRACTED", "source_file": "D:\\Padhai\\Style-Sync-AI\\DOSSIER.md", "source_location": "L207", "weight": 1.0}, {"source": "style_sync_ai_dossier_4_backend_deep_dive", "target": "style_sync_ai_dossier_middleware", "relation": "contains", "confidence": "EXTRACTED", "source_file": "D:\\Padhai\\Style-Sync-AI\\DOSSIER.md", "source_location": "L210", "weight": 1.0}, {"source": "style_sync_ai_dossier_4_backend_deep_dive", "target": "style_sync_ai_dossier_logging", "relation": "contains", "confidence": "EXTRACTED", "source_file": "D:\\Padhai\\Style-Sync-AI\\DOSSIER.md", "source_location": "L213", "weight": 1.0}, {"source": "style_sync_ai_dossier_4_backend_deep_dive", "target": "style_sync_ai_dossier_error_handling_216", "relation": "contains", "confidence": "EXTRACTED", "source_file": "D:\\Padhai\\Style-Sync-AI\\DOSSIER.md", "source_location": "L216", "weight": 1.0}, {"source": "style_sync_ai_dossier_4_backend_deep_dive", "target": "style_sync_ai_dossier_rate_limiting", "relation": "contains", "confidence": "EXTRACTED", "source_file": "D:\\Padhai\\Style-Sync-AI\\DOSSIER.md", "source_location": "L219", "weight": 1.0}, {"source": "style_sync_ai_dossier_4_backend_deep_dive", "target": "style_sync_ai_dossier_validation", "relation": "contains", "confidence": "EXTRACTED", "source_file": "D:\\Padhai\\Style-Sync-AI\\DOSSIER.md", "source_location": "L223", "weight": 1.0}, {"source": "style_sync_ai_dossier_4_backend_deep_dive", "target": "style_sync_ai_dossier_background_jobs", "relation": "contains", "confidence": "EXTRACTED", "source_file": "D:\\Padhai\\Style-Sync-AI\\DOSSIER.md", "source_location": "L226", "weight": 1.0}, {"source": "style_sync_ai_dossier_4_backend_deep_dive", "target": "style_sync_ai_dossier_caching_message_queues_websockets", "relation": "contains", "confidence": "EXTRACTED", "source_file": "D:\\Padhai\\Style-Sync-AI\\DOSSIER.md", "source_location": "L229", "weight": 1.0}, {"source": "d_padhai_style_sync_ai_dossier_md", "target": "style_sync_ai_dossier_5_database_deep_dive", "relation": "contains", "confidence": "EXTRACTED", "source_file": "D:\\Padhai\\Style-Sync-AI\\DOSSIER.md", "source_location": "L234", "weight": 1.0}, {"source": "style_sync_ai_dossier_5_database_deep_dive", "target": "style_sync_ai_dossier_database_choice_postgresql_prisma_7", "relation": "contains", "confidence": "EXTRACTED", "source_file": "D:\\Padhai\\Style-Sync-AI\\DOSSIER.md", "source_location": "L236", "weight": 1.0}, {"source": "style_sync_ai_dossier_5_database_deep_dive", "target": "style_sync_ai_dossier_schema_design_models", "relation": "contains", "confidence": "EXTRACTED", "source_file": "D:\\Padhai\\Style-Sync-AI\\DOSSIER.md", "source_location": "L240", "weight": 1.0}, {"source": "style_sync_ai_dossier_5_database_deep_dive", "target": "style_sync_ai_dossier_relationships", "relation": "contains", "confidence": "EXTRACTED", "source_file": "D:\\Padhai\\Style-Sync-AI\\DOSSIER.md", "source_location": "L243", "weight": 1.0}, {"source": "style_sync_ai_dossier_5_database_deep_dive", "target": "style_sync_ai_dossier_indexing", "relation": "contains", "confidence": "EXTRACTED", "source_file": "D:\\Padhai\\Style-Sync-AI\\DOSSIER.md", "source_location": "L249", "weight": 1.0}, {"source": "style_sync_ai_dossier_5_database_deep_dive", "target": "style_sync_ai_dossier_query_optimization", "relation": "contains", "confidence": "EXTRACTED", "source_file": "D:\\Padhai\\Style-Sync-AI\\DOSSIER.md", "source_location": "L252", "weight": 1.0}, {"source": "style_sync_ai_dossier_5_database_deep_dive", "target": "style_sync_ai_dossier_scaling_strategy", "relation": "contains", "confidence": "EXTRACTED", "source_file": "D:\\Padhai\\Style-Sync-AI\\DOSSIER.md", "source_location": "L255", "weight": 1.0}, {"source": "style_sync_ai_dossier_5_database_deep_dive", "target": "style_sync_ai_dossier_backup_consistency_transactions", "relation": "contains", "confidence": "EXTRACTED", "source_file": "D:\\Padhai\\Style-Sync-AI\\DOSSIER.md", "source_location": "L258", "weight": 1.0}, {"source": "style_sync_ai_dossier_5_database_deep_dive", "target": "style_sync_ai_dossier_er_diagram", "relation": "contains", "confidence": "EXTRACTED", "source_file": "D:\\Padhai\\Style-Sync-AI\\DOSSIER.md", "source_location": "L261", "weight": 1.0}, {"source": "style_sync_ai_dossier_5_database_deep_dive", "target": "style_sync_ai_dossier_sample_tables", "relation": "contains", "confidence": "EXTRACTED", "source_file": "D:\\Padhai\\Style-Sync-AI\\DOSSIER.md", "source_location": "L276", "weight": 1.0}, {"source": "style_sync_ai_dossier_5_database_deep_dive", "target": "style_sync_ai_dossier_common_queries", "relation": "contains", "confidence": "EXTRACTED", "source_file": "D:\\Padhai\\Style-Sync-AI\\DOSSIER.md", "source_location": "L289", "weight": 1.0}, {"source": "d_padhai_style_sync_ai_dossier_md", "target": "style_sync_ai_dossier_6_technology_breakdown", "relation": "contains", "confidence": "EXTRACTED", "source_file": "D:\\Padhai\\Style-Sync-AI\\DOSSIER.md", "source_location": "L303", "weight": 1.0}, {"source": "d_padhai_style_sync_ai_dossier_md", "target": "style_sync_ai_dossier_7_feature_by_feature_analysis", "relation": "contains", "confidence": "EXTRACTED", "source_file": "D:\\Padhai\\Style-Sync-AI\\DOSSIER.md", "source_location": "L325", "weight": 1.0}, {"source": "style_sync_ai_dossier_7_feature_by_feature_analysis", "target": "style_sync_ai_dossier_a_garment_upload_ai_classification", "relation": "contains", "confidence": "EXTRACTED", "source_file": "D:\\Padhai\\Style-Sync-AI\\DOSSIER.md", "source_location": "L327", "weight": 1.0}, {"source": "style_sync_ai_dossier_7_feature_by_feature_analysis", "target": "style_sync_ai_dossier_b_ai_outfit_generation", "relation": "contains", "confidence": "EXTRACTED", "source_file": "D:\\Padhai\\Style-Sync-AI\\DOSSIER.md", "source_location": "L335", "weight": 1.0}, {"source": "style_sync_ai_dossier_7_feature_by_feature_analysis", "target": "style_sync_ai_dossier_c_weather_occasion_recommendation_engine_the_crown_jewel", "relation": "contains", "confidence": "EXTRACTED", "source_file": "D:\\Padhai\\Style-Sync-AI\\DOSSIER.md", "source_location": "L342", "weight": 1.0}, {"source": "style_sync_ai_dossier_7_feature_by_feature_analysis", "target": "style_sync_ai_dossier_d_preference_learning_closed_loop", "relation": "contains", "confidence": "EXTRACTED", "source_file": "D:\\Padhai\\Style-Sync-AI\\DOSSIER.md", "source_location": "L354", "weight": 1.0}, {"source": "style_sync_ai_dossier_7_feature_by_feature_analysis", "target": "style_sync_ai_dossier_e_weekly_planner_wear_history_insights", "relation": "contains", "confidence": "EXTRACTED", "source_file": "D:\\Padhai\\Style-Sync-AI\\DOSSIER.md", "source_location": "L360", "weight": 1.0}, {"source": "d_padhai_style_sync_ai_dossier_md", "target": "style_sync_ai_dossier_8_security_analysis", "relation": "contains", "confidence": "EXTRACTED", "source_file": "D:\\Padhai\\Style-Sync-AI\\DOSSIER.md", "source_location": "L367", "weight": 1.0}, {"source": "d_padhai_style_sync_ai_dossier_md", "target": "style_sync_ai_dossier_9_scalability_discussion", "relation": "contains", "confidence": "EXTRACTED", "source_file": "D:\\Padhai\\Style-Sync-AI\\DOSSIER.md", "source_location": "L390", "weight": 1.0}, {"source": "d_padhai_style_sync_ai_dossier_md", "target": "style_sync_ai_dossier_10_deployment_devops", "relation": "contains", "confidence": "EXTRACTED", "source_file": "D:\\Padhai\\Style-Sync-AI\\DOSSIER.md", "source_location": "L411", "weight": 1.0}, {"source": "d_padhai_style_sync_ai_dossier_md", "target": "style_sync_ai_dossier_11_design_decisions", "relation": "contains", "confidence": "EXTRACTED", "source_file": "D:\\Padhai\\Style-Sync-AI\\DOSSIER.md", "source_location": "L428", "weight": 1.0}, {"source": "d_padhai_style_sync_ai_dossier_md", "target": "style_sync_ai_dossier_12_challenges_problem_solving_10", "relation": "contains", "confidence": "EXTRACTED", "source_file": "D:\\Padhai\\Style-Sync-AI\\DOSSIER.md", "source_location": "L440", "weight": 1.0}, {"source": "d_padhai_style_sync_ai_dossier_md", "target": "style_sync_ai_dossier_13_resume_discussion_preparation", "relation": "contains", "confidence": "EXTRACTED", "source_file": "D:\\Padhai\\Style-Sync-AI\\DOSSIER.md", "source_location": "L455", "weight": 1.0}, {"source": "style_sync_ai_dossier_13_resume_discussion_preparation", "target": "style_sync_ai_dossier_tell_me_about_this_project", "relation": "contains", "confidence": "EXTRACTED", "source_file": "D:\\Padhai\\Style-Sync-AI\\DOSSIER.md", "source_location": "L457", "weight": 1.0}, {"source": "style_sync_ai_dossier_13_resume_discussion_preparation", "target": "style_sync_ai_dossier_why_did_you_build_it", "relation": "contains", "confidence": "EXTRACTED", "source_file": "D:\\Padhai\\Style-Sync-AI\\DOSSIER.md", "source_location": "L462", "weight": 1.0}, {"source": "style_sync_ai_dossier_13_resume_discussion_preparation", "target": "style_sync_ai_dossier_what_was_your_contribution", "relation": "contains", "confidence": "EXTRACTED", "source_file": "D:\\Padhai\\Style-Sync-AI\\DOSSIER.md", "source_location": "L466", "weight": 1.0}, {"source": "style_sync_ai_dossier_13_resume_discussion_preparation", "target": "style_sync_ai_dossier_hardest_problem", "relation": "contains", "confidence": "EXTRACTED", "source_file": "D:\\Padhai\\Style-Sync-AI\\DOSSIER.md", "source_location": "L469", "weight": 1.0}, {"source": "style_sync_ai_dossier_13_resume_discussion_preparation", "target": "style_sync_ai_dossier_what_would_you_improve", "relation": "contains", "confidence": "EXTRACTED", "source_file": "D:\\Padhai\\Style-Sync-AI\\DOSSIER.md", "source_location": "L473", "weight": 1.0}, {"source": "style_sync_ai_dossier_13_resume_discussion_preparation", "target": "style_sync_ai_dossier_what_did_you_learn", "relation": "contains", "confidence": "EXTRACTED", "source_file": "D:\\Padhai\\Style-Sync-AI\\DOSSIER.md", "source_location": "L476", "weight": 1.0}, {"source": "d_padhai_style_sync_ai_dossier_md", "target": "style_sync_ai_dossier_14_technical_interview_questions", "relation": "contains", "confidence": "EXTRACTED", "source_file": "D:\\Padhai\\Style-Sync-AI\\DOSSIER.md", "source_location": "L481", "weight": 1.0}, {"source": "style_sync_ai_dossier_14_technical_interview_questions", "target": "style_sync_ai_dossier_beginner_20", "relation": "contains", "confidence": "EXTRACTED", "source_file": "D:\\Padhai\\Style-Sync-AI\\DOSSIER.md", "source_location": "L483", "weight": 1.0}, {"source": "style_sync_ai_dossier_14_technical_interview_questions", "target": "style_sync_ai_dossier_intermediate_30", "relation": "contains", "confidence": "EXTRACTED", "source_file": "D:\\Padhai\\Style-Sync-AI\\DOSSIER.md", "source_location": "L505", "weight": 1.0}, {"source": "style_sync_ai_dossier_14_technical_interview_questions", "target": "style_sync_ai_dossier_advanced_30", "relation": "contains", "confidence": "EXTRACTED", "source_file": "D:\\Padhai\\Style-Sync-AI\\DOSSIER.md", "source_location": "L537", "weight": 1.0}, {"source": "d_padhai_style_sync_ai_dossier_md", "target": "style_sync_ai_dossier_15_project_defense_round_25_skeptical_questions_answers", "relation": "contains", "confidence": "EXTRACTED", "source_file": "D:\\Padhai\\Style-Sync-AI\\DOSSIER.md", "source_location": "L571", "weight": 1.0}, {"source": "d_padhai_style_sync_ai_dossier_md", "target": "style_sync_ai_dossier_16_hidden_follow_up_questions_3_per_key_answer", "relation": "contains", "confidence": "EXTRACTED", "source_file": "D:\\Padhai\\Style-Sync-AI\\DOSSIER.md", "source_location": "L601", "weight": 1.0}, {"source": "d_padhai_style_sync_ai_dossier_md", "target": "style_sync_ai_dossier_17_production_grade_improvements", "relation": "contains", "confidence": "EXTRACTED", "source_file": "D:\\Padhai\\Style-Sync-AI\\DOSSIER.md", "source_location": "L630", "weight": 1.0}, {"source": "d_padhai_style_sync_ai_dossier_md", "target": "style_sync_ai_dossier_18_complete_viva_preparation_sheet_rapid_revision", "relation": "contains", "confidence": "EXTRACTED", "source_file": "D:\\Padhai\\Style-Sync-AI\\DOSSIER.md", "source_location": "L641", "weight": 1.0}, {"source": "d_padhai_style_sync_ai_dossier_md", "target": "style_sync_ai_dossier_19_knowledge_gaps_and_how_to_prepare", "relation": "contains", "confidence": "EXTRACTED", "source_file": "D:\\Padhai\\Style-Sync-AI\\DOSSIER.md", "source_location": "L654", "weight": 1.0}, {"source": "d_padhai_style_sync_ai_dossier_md", "target": "style_sync_ai_dossier_20_interview_readiness_score", "relation": "contains", "confidence": "EXTRACTED", "source_file": "D:\\Padhai\\Style-Sync-AI\\DOSSIER.md", "source_location": "L666", "weight": 1.0}], "input_tokens": 0, "output_tokens": 0}