{"nodes": [{"id": "d_padhai_style_sync_ai_context_feature_specs_30_community_style_feed_md", "label": "30-community-style-feed.md", "file_type": "document", "source_file": "D:\\Padhai\\Style-Sync-AI\\context\\feature-specs\\30-community-style-feed.md", "source_location": "L1"}, {"id": "feature_specs_30_community_style_feed_community_style_feed_f5", "label": "Community Style Feed (F5)", "file_type": "document", "source_file": "D:\\Padhai\\Style-Sync-AI\\context\\feature-specs\\30-community-style-feed.md", "source_location": "L1"}, {"id": "feature_specs_30_community_style_feed_problem_being_solved", "label": "Problem Being Solved", "file_type": "document", "source_file": "D:\\Padhai\\Style-Sync-AI\\context\\feature-specs\\30-community-style-feed.md", "source_location": "L19"}, {"id": "feature_specs_30_community_style_feed_scope", "label": "Scope", "file_type": "document", "source_file": "D:\\Padhai\\Style-Sync-AI\\context\\feature-specs\\30-community-style-feed.md", "source_location": "L31"}, {"id": "feature_specs_30_community_style_feed_communityprofile_model_one_time_display_name_avatar_privacy_setup_gating_all_publishing", "label": "`CommunityProfile` model \u2014 one-time display name + avatar + privacy setup, gating all publishing", "file_type": "document", "source_file": "D:\\Padhai\\Style-Sync-AI\\context\\feature-specs\\30-community-style-feed.md", "source_location": "L35"}, {"id": "feature_specs_30_community_style_feed_communitypost_communitylike_inspirationsave_models", "label": "`CommunityPost` / `CommunityLike` / `InspirationSave` models", "file_type": "document", "source_file": "D:\\Padhai\\Style-Sync-AI\\context\\feature-specs\\30-community-style-feed.md", "source_location": "L36"}, {"id": "feature_specs_30_community_style_feed_post_get_api_community_profile_fetch_or_create_update_the_caller_s_own_profile", "label": "`POST/GET /api/community/profile` \u2014 fetch or create/update the caller's own profile", "file_type": "document", "source_file": "D:\\Padhai\\Style-Sync-AI\\context\\feature-specs\\30-community-style-feed.md", "source_location": "L37"}, {"id": "feature_specs_30_community_style_feed_get_post_api_community_feed_cursor_paginated_newest_capped_top_n_trending_and_publish", "label": "`GET/POST /api/community` \u2014 feed (cursor-paginated \"newest\", capped top-N \"trending\") and publish", "file_type": "document", "source_file": "D:\\Padhai\\Style-Sync-AI\\context\\feature-specs\\30-community-style-feed.md", "source_location": "L38"}, {"id": "feature_specs_30_community_style_feed_post_api_community_id_like_post_api_community_id_save_delete_api_community_id", "label": "`POST /api/community/[id]/like`, `POST /api/community/[id]/save`, `DELETE /api/community/[id]`", "file_type": "document", "source_file": "D:\\Padhai\\Style-Sync-AI\\context\\feature-specs\\30-community-style-feed.md", "source_location": "L39"}, {"id": "feature_specs_30_community_style_feed_publish_to_community_action_on_lookbook_id_for_entries_with_isshareable_true", "label": "\"Publish to Community\" action on `/lookbook/[id]` for entries with `isShareable: true`", "file_type": "document", "source_file": "D:\\Padhai\\Style-Sync-AI\\context\\feature-specs\\30-community-style-feed.md", "source_location": "L40"}, {"id": "feature_specs_30_community_style_feed_community_route_feed_saved_tab_switcher_occasion_filter_trending_toggle", "label": "`/community` route \u2014 Feed / Saved tab switcher, occasion filter, trending toggle", "file_type": "document", "source_file": "D:\\Padhai\\Style-Sync-AI\\context\\feature-specs\\30-community-style-feed.md", "source_location": "L41"}, {"id": "feature_specs_30_community_style_feed_new_dependencies", "label": "New Dependencies", "file_type": "document", "source_file": "D:\\Padhai\\Style-Sync-AI\\context\\feature-specs\\30-community-style-feed.md", "source_location": "L64"}, {"id": "feature_specs_30_community_style_feed_database_changes", "label": "Database Changes", "file_type": "document", "source_file": "D:\\Padhai\\Style-Sync-AI\\context\\feature-specs\\30-community-style-feed.md", "source_location": "L76"}, {"id": "feature_specs_30_community_style_feed_backend", "label": "Backend", "file_type": "document", "source_file": "D:\\Padhai\\Style-Sync-AI\\context\\feature-specs\\30-community-style-feed.md", "source_location": "L175"}, {"id": "feature_specs_30_community_style_feed_types_backend_src_types_index_ts", "label": "Types (`backend/src/types/index.ts`)", "file_type": "document", "source_file": "D:\\Padhai\\Style-Sync-AI\\context\\feature-specs\\30-community-style-feed.md", "source_location": "L177"}, {"id": "feature_specs_30_community_style_feed_zod_schemas_frontend_lib_schemas_ts", "label": "Zod schemas (`frontend/lib/schemas.ts`)", "file_type": "document", "source_file": "D:\\Padhai\\Style-Sync-AI\\context\\feature-specs\\30-community-style-feed.md", "source_location": "L214"}, {"id": "feature_specs_30_community_style_feed_get_post_api_community_profile_route_ts", "label": "`GET/POST /api/community/profile/route.ts`", "file_type": "document", "source_file": "D:\\Padhai\\Style-Sync-AI\\context\\feature-specs\\30-community-style-feed.md", "source_location": "L227"}, {"id": "feature_specs_30_community_style_feed_get_post_api_community_route_ts", "label": "`GET/POST /api/community/route.ts`", "file_type": "document", "source_file": "D:\\Padhai\\Style-Sync-AI\\context\\feature-specs\\30-community-style-feed.md", "source_location": "L236"}, {"id": "feature_specs_30_community_style_feed_post_api_community_id_like_route_ts_and_save_route_ts", "label": "`POST /api/community/[id]/like/route.ts` and `.../save/route.ts`", "file_type": "document", "source_file": "D:\\Padhai\\Style-Sync-AI\\context\\feature-specs\\30-community-style-feed.md", "source_location": "L281"}, {"id": "feature_specs_30_community_style_feed_delete_api_community_id_route_ts", "label": "`DELETE /api/community/[id]/route.ts`", "file_type": "document", "source_file": "D:\\Padhai\\Style-Sync-AI\\context\\feature-specs\\30-community-style-feed.md", "source_location": "L290"}, {"id": "feature_specs_30_community_style_feed_frontend", "label": "Frontend", "file_type": "document", "source_file": "D:\\Padhai\\Style-Sync-AI\\context\\feature-specs\\30-community-style-feed.md", "source_location": "L298"}, {"id": "feature_specs_30_community_style_feed_files", "label": "Files", "file_type": "document", "source_file": "D:\\Padhai\\Style-Sync-AI\\context\\feature-specs\\30-community-style-feed.md", "source_location": "L300"}, {"id": "feature_specs_30_community_style_feed_publish_entry_point", "label": "Publish entry point", "file_type": "document", "source_file": "D:\\Padhai\\Style-Sync-AI\\context\\feature-specs\\30-community-style-feed.md", "source_location": "L353"}, {"id": "feature_specs_30_community_style_feed_navigation", "label": "Navigation", "file_type": "document", "source_file": "D:\\Padhai\\Style-Sync-AI\\context\\feature-specs\\30-community-style-feed.md", "source_location": "L363"}, {"id": "feature_specs_30_community_style_feed_technical_notes_deviations_from_the_phase_3_brief", "label": "Technical Notes \u2014 Deviations from the Phase 3 Brief", "file_type": "document", "source_file": "D:\\Padhai\\Style-Sync-AI\\context\\feature-specs\\30-community-style-feed.md", "source_location": "L372"}, {"id": "feature_specs_30_community_style_feed_files_to_create", "label": "Files to Create", "file_type": "document", "source_file": "D:\\Padhai\\Style-Sync-AI\\context\\feature-specs\\30-community-style-feed.md", "source_location": "L392"}, {"id": "feature_specs_30_community_style_feed_files_to_modify", "label": "Files to Modify", "file_type": "document", "source_file": "D:\\Padhai\\Style-Sync-AI\\context\\feature-specs\\30-community-style-feed.md", "source_location": "L408"}, {"id": "feature_specs_30_community_style_feed_constraints", "label": "Constraints", "file_type": "document", "source_file": "D:\\Padhai\\Style-Sync-AI\\context\\feature-specs\\30-community-style-feed.md", "source_location": "L427"}, {"id": "feature_specs_30_community_style_feed_check_when_done", "label": "Check When Done", "file_type": "document", "source_file": "D:\\Padhai\\Style-Sync-AI\\context\\feature-specs\\30-community-style-feed.md", "source_location": "L447"}], "edges": [{"source": "d_padhai_style_sync_ai_context_feature_specs_30_community_style_feed_md", "target": "feature_specs_30_community_style_feed_community_style_feed_f5", "relation": "contains", "confidence": "EXTRACTED", "source_file": "D:\\Padhai\\Style-Sync-AI\\context\\feature-specs\\30-community-style-feed.md", "source_location": "L1", "weight": 1.0}, {"source": "d_padhai_style_sync_ai_context_feature_specs_30_community_style_feed_md", "target": "feature_specs_30_community_style_feed_problem_being_solved", "relation": "contains", "confidence": "EXTRACTED", "source_file": "D:\\Padhai\\Style-Sync-AI\\context\\feature-specs\\30-community-style-feed.md", "source_location": "L19", "weight": 1.0}, {"source": "d_padhai_style_sync_ai_context_feature_specs_30_community_style_feed_md", "target": "feature_specs_30_community_style_feed_scope", "relation": "contains", "confidence": "EXTRACTED", "source_file": "D:\\Padhai\\Style-Sync-AI\\context\\feature-specs\\30-community-style-feed.md", "source_location": "L31", "weight": 1.0}, {"source": "feature_specs_30_community_style_feed_scope", "target": "feature_specs_30_community_style_feed_communityprofile_model_one_time_display_name_avatar_privacy_setup_gating_all_publishing", "relation": "contains", "confidence": "EXTRACTED", "source_file": "D:\\Padhai\\Style-Sync-AI\\context\\feature-specs\\30-community-style-feed.md", "source_location": "L35", "weight": 1.0}, {"source": "feature_specs_30_community_style_feed_scope", "target": "feature_specs_30_community_style_feed_communitypost_communitylike_inspirationsave_models", "relation": "contains", "confidence": "EXTRACTED", "source_file": "D:\\Padhai\\Style-Sync-AI\\context\\feature-specs\\30-community-style-feed.md", "source_location": "L36", "weight": 1.0}, {"source": "feature_specs_30_community_style_feed_scope", "target": "feature_specs_30_community_style_feed_post_get_api_community_profile_fetch_or_create_update_the_caller_s_own_profile", "relation": "contains", "confidence": "EXTRACTED", "source_file": "D:\\Padhai\\Style-Sync-AI\\context\\feature-specs\\30-community-style-feed.md", "source_location": "L37", "weight": 1.0}, {"source": "feature_specs_30_community_style_feed_scope", "target": "feature_specs_30_community_style_feed_get_post_api_community_feed_cursor_paginated_newest_capped_top_n_trending_and_publish", "relation": "contains", "confidence": "EXTRACTED", "source_file": "D:\\Padhai\\Style-Sync-AI\\context\\feature-specs\\30-community-style-feed.md", "source_location": "L38", "weight": 1.0}, {"source": "feature_specs_30_community_style_feed_scope", "target": "feature_specs_30_community_style_feed_post_api_community_id_like_post_api_community_id_save_delete_api_community_id", "relation": "contains", "confidence": "EXTRACTED", "source_file": "D:\\Padhai\\Style-Sync-AI\\context\\feature-specs\\30-community-style-feed.md", "source_location": "L39", "weight": 1.0}, {"source": "feature_specs_30_community_style_feed_scope", "target": "feature_specs_30_community_style_feed_publish_to_community_action_on_lookbook_id_for_entries_with_isshareable_true", "relation": "contains", "confidence": "EXTRACTED", "source_file": "D:\\Padhai\\Style-Sync-AI\\context\\feature-specs\\30-community-style-feed.md", "source_location": "L40", "weight": 1.0}, {"source": "feature_specs_30_community_style_feed_scope", "target": "feature_specs_30_community_style_feed_community_route_feed_saved_tab_switcher_occasion_filter_trending_toggle", "relation": "contains", "confidence": "EXTRACTED", "source_file": "D:\\Padhai\\Style-Sync-AI\\context\\feature-specs\\30-community-style-feed.md", "source_location": "L41", "weight": 1.0}, {"source": "d_padhai_style_sync_ai_context_feature_specs_30_community_style_feed_md", "target": "feature_specs_30_community_style_feed_new_dependencies", "relation": "contains", "confidence": "EXTRACTED", "source_file": "D:\\Padhai\\Style-Sync-AI\\context\\feature-specs\\30-community-style-feed.md", "source_location": "L64", "weight": 1.0}, {"source": "d_padhai_style_sync_ai_context_feature_specs_30_community_style_feed_md", "target": "feature_specs_30_community_style_feed_database_changes", "relation": "contains", "confidence": "EXTRACTED", "source_file": "D:\\Padhai\\Style-Sync-AI\\context\\feature-specs\\30-community-style-feed.md", "source_location": "L76", "weight": 1.0}, {"source": "d_padhai_style_sync_ai_context_feature_specs_30_community_style_feed_md", "target": "feature_specs_30_community_style_feed_backend", "relation": "contains", "confidence": "EXTRACTED", "source_file": "D:\\Padhai\\Style-Sync-AI\\context\\feature-specs\\30-community-style-feed.md", "source_location": "L175", "weight": 1.0}, {"source": "feature_specs_30_community_style_feed_backend", "target": "feature_specs_30_community_style_feed_types_backend_src_types_index_ts", "relation": "contains", "confidence": "EXTRACTED", "source_file": "D:\\Padhai\\Style-Sync-AI\\context\\feature-specs\\30-community-style-feed.md", "source_location": "L177", "weight": 1.0}, {"source": "feature_specs_30_community_style_feed_backend", "target": "feature_specs_30_community_style_feed_zod_schemas_frontend_lib_schemas_ts", "relation": "contains", "confidence": "EXTRACTED", "source_file": "D:\\Padhai\\Style-Sync-AI\\context\\feature-specs\\30-community-style-feed.md", "source_location": "L214", "weight": 1.0}, {"source": "feature_specs_30_community_style_feed_backend", "target": "feature_specs_30_community_style_feed_get_post_api_community_profile_route_ts", "relation": "contains", "confidence": "EXTRACTED", "source_file": "D:\\Padhai\\Style-Sync-AI\\context\\feature-specs\\30-community-style-feed.md", "source_location": "L227", "weight": 1.0}, {"source": "feature_specs_30_community_style_feed_backend", "target": "feature_specs_30_community_style_feed_get_post_api_community_route_ts", "relation": "contains", "confidence": "EXTRACTED", "source_file": "D:\\Padhai\\Style-Sync-AI\\context\\feature-specs\\30-community-style-feed.md", "source_location": "L236", "weight": 1.0}, {"source": "feature_specs_30_community_style_feed_backend", "target": "feature_specs_30_community_style_feed_post_api_community_id_like_route_ts_and_save_route_ts", "relation": "contains", "confidence": "EXTRACTED", "source_file": "D:\\Padhai\\Style-Sync-AI\\context\\feature-specs\\30-community-style-feed.md", "source_location": "L281", "weight": 1.0}, {"source": "feature_specs_30_community_style_feed_backend", "target": "feature_specs_30_community_style_feed_delete_api_community_id_route_ts", "relation": "contains", "confidence": "EXTRACTED", "source_file": "D:\\Padhai\\Style-Sync-AI\\context\\feature-specs\\30-community-style-feed.md", "source_location": "L290", "weight": 1.0}, {"source": "d_padhai_style_sync_ai_context_feature_specs_30_community_style_feed_md", "target": "feature_specs_30_community_style_feed_frontend", "relation": "contains", "confidence": "EXTRACTED", "source_file": "D:\\Padhai\\Style-Sync-AI\\context\\feature-specs\\30-community-style-feed.md", "source_location": "L298", "weight": 1.0}, {"source": "feature_specs_30_community_style_feed_frontend", "target": "feature_specs_30_community_style_feed_files", "relation": "contains", "confidence": "EXTRACTED", "source_file": "D:\\Padhai\\Style-Sync-AI\\context\\feature-specs\\30-community-style-feed.md", "source_location": "L300", "weight": 1.0}, {"source": "feature_specs_30_community_style_feed_frontend", "target": "feature_specs_30_community_style_feed_publish_entry_point", "relation": "contains", "confidence": "EXTRACTED", "source_file": "D:\\Padhai\\Style-Sync-AI\\context\\feature-specs\\30-community-style-feed.md", "source_location": "L353", "weight": 1.0}, {"source": "feature_specs_30_community_style_feed_frontend", "target": "feature_specs_30_community_style_feed_navigation", "relation": "contains", "confidence": "EXTRACTED", "source_file": "D:\\Padhai\\Style-Sync-AI\\context\\feature-specs\\30-community-style-feed.md", "source_location": "L363", "weight": 1.0}, {"source": "d_padhai_style_sync_ai_context_feature_specs_30_community_style_feed_md", "target": "feature_specs_30_community_style_feed_technical_notes_deviations_from_the_phase_3_brief", "relation": "contains", "confidence": "EXTRACTED", "source_file": "D:\\Padhai\\Style-Sync-AI\\context\\feature-specs\\30-community-style-feed.md", "source_location": "L372", "weight": 1.0}, {"source": "d_padhai_style_sync_ai_context_feature_specs_30_community_style_feed_md", "target": "feature_specs_30_community_style_feed_files_to_create", "relation": "contains", "confidence": "EXTRACTED", "source_file": "D:\\Padhai\\Style-Sync-AI\\context\\feature-specs\\30-community-style-feed.md", "source_location": "L392", "weight": 1.0}, {"source": "d_padhai_style_sync_ai_context_feature_specs_30_community_style_feed_md", "target": "feature_specs_30_community_style_feed_files_to_modify", "relation": "contains", "confidence": "EXTRACTED", "source_file": "D:\\Padhai\\Style-Sync-AI\\context\\feature-specs\\30-community-style-feed.md", "source_location": "L408", "weight": 1.0}, {"source": "d_padhai_style_sync_ai_context_feature_specs_30_community_style_feed_md", "target": "feature_specs_30_community_style_feed_constraints", "relation": "contains", "confidence": "EXTRACTED", "source_file": "D:\\Padhai\\Style-Sync-AI\\context\\feature-specs\\30-community-style-feed.md", "source_location": "L427", "weight": 1.0}, {"source": "d_padhai_style_sync_ai_context_feature_specs_30_community_style_feed_md", "target": "feature_specs_30_community_style_feed_check_when_done", "relation": "contains", "confidence": "EXTRACTED", "source_file": "D:\\Padhai\\Style-Sync-AI\\context\\feature-specs\\30-community-style-feed.md", "source_location": "L447", "weight": 1.0}], "input_tokens": 0, "output_tokens": 0}