{"nodes": [{"id": "d_padhai_style_sync_ai_context_feature_specs_23_redis_cache_rate_limiting_md", "label": "23-redis-cache-rate-limiting.md", "file_type": "document", "source_file": "D:\\Padhai\\Style-Sync-AI\\context\\feature-specs\\23-redis-cache-rate-limiting.md", "source_location": "L1"}, {"id": "feature_specs_23_redis_cache_rate_limiting_redis_backed_cache_rate_limiting_f7", "label": "Redis-backed Cache & Rate Limiting (F7)", "file_type": "document", "source_file": "D:\\Padhai\\Style-Sync-AI\\context\\feature-specs\\23-redis-cache-rate-limiting.md", "source_location": "L1"}, {"id": "feature_specs_23_redis_cache_rate_limiting_problem_being_solved", "label": "Problem Being Solved", "file_type": "document", "source_file": "D:\\Padhai\\Style-Sync-AI\\context\\feature-specs\\23-redis-cache-rate-limiting.md", "source_location": "L17"}, {"id": "feature_specs_23_redis_cache_rate_limiting_scope", "label": "Scope", "file_type": "document", "source_file": "D:\\Padhai\\Style-Sync-AI\\context\\feature-specs\\23-redis-cache-rate-limiting.md", "source_location": "L35"}, {"id": "feature_specs_23_redis_cache_rate_limiting_redis_client_singleton_lib_redis_ts", "label": "Redis client singleton (`lib/redis.ts`)", "file_type": "document", "source_file": "D:\\Padhai\\Style-Sync-AI\\context\\feature-specs\\23-redis-cache-rate-limiting.md", "source_location": "L39"}, {"id": "feature_specs_23_redis_cache_rate_limiting_sliding_window_rate_limiter_backed_by_upstash_redis", "label": "Sliding-window rate limiter backed by Upstash Redis", "file_type": "document", "source_file": "D:\\Padhai\\Style-Sync-AI\\context\\feature-specs\\23-redis-cache-rate-limiting.md", "source_location": "L40"}, {"id": "feature_specs_23_redis_cache_rate_limiting_weather_cache_backed_by_redis_with_15_min_ttl", "label": "Weather cache backed by Redis with 15-min TTL", "file_type": "document", "source_file": "D:\\Padhai\\Style-Sync-AI\\context\\feature-specs\\23-redis-cache-rate-limiting.md", "source_location": "L41"}, {"id": "feature_specs_23_redis_cache_rate_limiting_style_dna_generation_cache_backed_by_redis_with_24_hour_ttl_f1_prep", "label": "Style DNA generation cache backed by Redis with 24-hour TTL (F1 prep)", "file_type": "document", "source_file": "D:\\Padhai\\Style-Sync-AI\\context\\feature-specs\\23-redis-cache-rate-limiting.md", "source_location": "L42"}, {"id": "feature_specs_23_redis_cache_rate_limiting_capsule_audit_result_cache_backed_by_redis_with_6_hour_ttl_f2_prep", "label": "Capsule Audit result cache backed by Redis with 6-hour TTL (F2 prep)", "file_type": "document", "source_file": "D:\\Padhai\\Style-Sync-AI\\context\\feature-specs\\23-redis-cache-rate-limiting.md", "source_location": "L43"}, {"id": "feature_specs_23_redis_cache_rate_limiting_new_dependencies", "label": "New Dependencies", "file_type": "document", "source_file": "D:\\Padhai\\Style-Sync-AI\\context\\feature-specs\\23-redis-cache-rate-limiting.md", "source_location": "L55"}, {"id": "feature_specs_23_redis_cache_rate_limiting_new_environment_variables", "label": "New Environment Variables", "file_type": "document", "source_file": "D:\\Padhai\\Style-Sync-AI\\context\\feature-specs\\23-redis-cache-rate-limiting.md", "source_location": "L70"}, {"id": "feature_specs_23_redis_cache_rate_limiting_redis_client_singleton", "label": "Redis Client Singleton", "file_type": "document", "source_file": "D:\\Padhai\\Style-Sync-AI\\context\\feature-specs\\23-redis-cache-rate-limiting.md", "source_location": "L82"}, {"id": "feature_specs_23_redis_cache_rate_limiting_rate_limiter", "label": "Rate Limiter", "file_type": "document", "source_file": "D:\\Padhai\\Style-Sync-AI\\context\\feature-specs\\23-redis-cache-rate-limiting.md", "source_location": "L111"}, {"id": "feature_specs_23_redis_cache_rate_limiting_current_implementation", "label": "Current Implementation", "file_type": "document", "source_file": "D:\\Padhai\\Style-Sync-AI\\context\\feature-specs\\23-redis-cache-rate-limiting.md", "source_location": "L113"}, {"id": "feature_specs_23_redis_cache_rate_limiting_new_implementation", "label": "New Implementation", "file_type": "document", "source_file": "D:\\Padhai\\Style-Sync-AI\\context\\feature-specs\\23-redis-cache-rate-limiting.md", "source_location": "L122"}, {"id": "feature_specs_23_redis_cache_rate_limiting_call_sites_to_update", "label": "Call sites to update", "file_type": "document", "source_file": "D:\\Padhai\\Style-Sync-AI\\context\\feature-specs\\23-redis-cache-rate-limiting.md", "source_location": "L183"}, {"id": "feature_specs_23_redis_cache_rate_limiting_weather_cache", "label": "Weather Cache", "file_type": "document", "source_file": "D:\\Padhai\\Style-Sync-AI\\context\\feature-specs\\23-redis-cache-rate-limiting.md", "source_location": "L206"}, {"id": "feature_specs_23_redis_cache_rate_limiting_current_implementation_208", "label": "Current Implementation", "file_type": "document", "source_file": "D:\\Padhai\\Style-Sync-AI\\context\\feature-specs\\23-redis-cache-rate-limiting.md", "source_location": "L208"}, {"id": "feature_specs_23_redis_cache_rate_limiting_new_implementation_218", "label": "New Implementation", "file_type": "document", "source_file": "D:\\Padhai\\Style-Sync-AI\\context\\feature-specs\\23-redis-cache-rate-limiting.md", "source_location": "L218"}, {"id": "feature_specs_23_redis_cache_rate_limiting_style_dna_cache_f1_preparation", "label": "Style DNA Cache (F1 preparation)", "file_type": "document", "source_file": "D:\\Padhai\\Style-Sync-AI\\context\\feature-specs\\23-redis-cache-rate-limiting.md", "source_location": "L266"}, {"id": "feature_specs_23_redis_cache_rate_limiting_capsule_audit_cache_f2_preparation", "label": "Capsule Audit Cache (F2 preparation)", "file_type": "document", "source_file": "D:\\Padhai\\Style-Sync-AI\\context\\feature-specs\\23-redis-cache-rate-limiting.md", "source_location": "L299"}, {"id": "feature_specs_23_redis_cache_rate_limiting_redis_key_namespace", "label": "Redis Key Namespace", "file_type": "document", "source_file": "D:\\Padhai\\Style-Sync-AI\\context\\feature-specs\\23-redis-cache-rate-limiting.md", "source_location": "L332"}, {"id": "feature_specs_23_redis_cache_rate_limiting_database_changes", "label": "Database Changes", "file_type": "document", "source_file": "D:\\Padhai\\Style-Sync-AI\\context\\feature-specs\\23-redis-cache-rate-limiting.md", "source_location": "L346"}, {"id": "feature_specs_23_redis_cache_rate_limiting_files_to_create", "label": "Files to Create", "file_type": "document", "source_file": "D:\\Padhai\\Style-Sync-AI\\context\\feature-specs\\23-redis-cache-rate-limiting.md", "source_location": "L352"}, {"id": "feature_specs_23_redis_cache_rate_limiting_files_to_modify", "label": "Files to Modify", "file_type": "document", "source_file": "D:\\Padhai\\Style-Sync-AI\\context\\feature-specs\\23-redis-cache-rate-limiting.md", "source_location": "L362"}, {"id": "feature_specs_23_redis_cache_rate_limiting_constraints", "label": "Constraints", "file_type": "document", "source_file": "D:\\Padhai\\Style-Sync-AI\\context\\feature-specs\\23-redis-cache-rate-limiting.md", "source_location": "L385"}, {"id": "feature_specs_23_redis_cache_rate_limiting_check_when_done", "label": "Check When Done", "file_type": "document", "source_file": "D:\\Padhai\\Style-Sync-AI\\context\\feature-specs\\23-redis-cache-rate-limiting.md", "source_location": "L398"}], "edges": [{"source": "d_padhai_style_sync_ai_context_feature_specs_23_redis_cache_rate_limiting_md", "target": "feature_specs_23_redis_cache_rate_limiting_redis_backed_cache_rate_limiting_f7", "relation": "contains", "confidence": "EXTRACTED", "source_file": "D:\\Padhai\\Style-Sync-AI\\context\\feature-specs\\23-redis-cache-rate-limiting.md", "source_location": "L1", "weight": 1.0}, {"source": "d_padhai_style_sync_ai_context_feature_specs_23_redis_cache_rate_limiting_md", "target": "feature_specs_23_redis_cache_rate_limiting_problem_being_solved", "relation": "contains", "confidence": "EXTRACTED", "source_file": "D:\\Padhai\\Style-Sync-AI\\context\\feature-specs\\23-redis-cache-rate-limiting.md", "source_location": "L17", "weight": 1.0}, {"source": "d_padhai_style_sync_ai_context_feature_specs_23_redis_cache_rate_limiting_md", "target": "feature_specs_23_redis_cache_rate_limiting_scope", "relation": "contains", "confidence": "EXTRACTED", "source_file": "D:\\Padhai\\Style-Sync-AI\\context\\feature-specs\\23-redis-cache-rate-limiting.md", "source_location": "L35", "weight": 1.0}, {"source": "feature_specs_23_redis_cache_rate_limiting_scope", "target": "feature_specs_23_redis_cache_rate_limiting_redis_client_singleton_lib_redis_ts", "relation": "contains", "confidence": "EXTRACTED", "source_file": "D:\\Padhai\\Style-Sync-AI\\context\\feature-specs\\23-redis-cache-rate-limiting.md", "source_location": "L39", "weight": 1.0}, {"source": "feature_specs_23_redis_cache_rate_limiting_scope", "target": "feature_specs_23_redis_cache_rate_limiting_sliding_window_rate_limiter_backed_by_upstash_redis", "relation": "contains", "confidence": "EXTRACTED", "source_file": "D:\\Padhai\\Style-Sync-AI\\context\\feature-specs\\23-redis-cache-rate-limiting.md", "source_location": "L40", "weight": 1.0}, {"source": "feature_specs_23_redis_cache_rate_limiting_scope", "target": "feature_specs_23_redis_cache_rate_limiting_weather_cache_backed_by_redis_with_15_min_ttl", "relation": "contains", "confidence": "EXTRACTED", "source_file": "D:\\Padhai\\Style-Sync-AI\\context\\feature-specs\\23-redis-cache-rate-limiting.md", "source_location": "L41", "weight": 1.0}, {"source": "feature_specs_23_redis_cache_rate_limiting_scope", "target": "feature_specs_23_redis_cache_rate_limiting_style_dna_generation_cache_backed_by_redis_with_24_hour_ttl_f1_prep", "relation": "contains", "confidence": "EXTRACTED", "source_file": "D:\\Padhai\\Style-Sync-AI\\context\\feature-specs\\23-redis-cache-rate-limiting.md", "source_location": "L42", "weight": 1.0}, {"source": "feature_specs_23_redis_cache_rate_limiting_scope", "target": "feature_specs_23_redis_cache_rate_limiting_capsule_audit_result_cache_backed_by_redis_with_6_hour_ttl_f2_prep", "relation": "contains", "confidence": "EXTRACTED", "source_file": "D:\\Padhai\\Style-Sync-AI\\context\\feature-specs\\23-redis-cache-rate-limiting.md", "source_location": "L43", "weight": 1.0}, {"source": "d_padhai_style_sync_ai_context_feature_specs_23_redis_cache_rate_limiting_md", "target": "feature_specs_23_redis_cache_rate_limiting_new_dependencies", "relation": "contains", "confidence": "EXTRACTED", "source_file": "D:\\Padhai\\Style-Sync-AI\\context\\feature-specs\\23-redis-cache-rate-limiting.md", "source_location": "L55", "weight": 1.0}, {"source": "d_padhai_style_sync_ai_context_feature_specs_23_redis_cache_rate_limiting_md", "target": "feature_specs_23_redis_cache_rate_limiting_new_environment_variables", "relation": "contains", "confidence": "EXTRACTED", "source_file": "D:\\Padhai\\Style-Sync-AI\\context\\feature-specs\\23-redis-cache-rate-limiting.md", "source_location": "L70", "weight": 1.0}, {"source": "d_padhai_style_sync_ai_context_feature_specs_23_redis_cache_rate_limiting_md", "target": "feature_specs_23_redis_cache_rate_limiting_redis_client_singleton", "relation": "contains", "confidence": "EXTRACTED", "source_file": "D:\\Padhai\\Style-Sync-AI\\context\\feature-specs\\23-redis-cache-rate-limiting.md", "source_location": "L82", "weight": 1.0}, {"source": "d_padhai_style_sync_ai_context_feature_specs_23_redis_cache_rate_limiting_md", "target": "feature_specs_23_redis_cache_rate_limiting_rate_limiter", "relation": "contains", "confidence": "EXTRACTED", "source_file": "D:\\Padhai\\Style-Sync-AI\\context\\feature-specs\\23-redis-cache-rate-limiting.md", "source_location": "L111", "weight": 1.0}, {"source": "feature_specs_23_redis_cache_rate_limiting_rate_limiter", "target": "feature_specs_23_redis_cache_rate_limiting_current_implementation", "relation": "contains", "confidence": "EXTRACTED", "source_file": "D:\\Padhai\\Style-Sync-AI\\context\\feature-specs\\23-redis-cache-rate-limiting.md", "source_location": "L113", "weight": 1.0}, {"source": "feature_specs_23_redis_cache_rate_limiting_rate_limiter", "target": "feature_specs_23_redis_cache_rate_limiting_new_implementation", "relation": "contains", "confidence": "EXTRACTED", "source_file": "D:\\Padhai\\Style-Sync-AI\\context\\feature-specs\\23-redis-cache-rate-limiting.md", "source_location": "L122", "weight": 1.0}, {"source": "feature_specs_23_redis_cache_rate_limiting_new_implementation", "target": "feature_specs_23_redis_cache_rate_limiting_call_sites_to_update", "relation": "contains", "confidence": "EXTRACTED", "source_file": "D:\\Padhai\\Style-Sync-AI\\context\\feature-specs\\23-redis-cache-rate-limiting.md", "source_location": "L183", "weight": 1.0}, {"source": "d_padhai_style_sync_ai_context_feature_specs_23_redis_cache_rate_limiting_md", "target": "feature_specs_23_redis_cache_rate_limiting_weather_cache", "relation": "contains", "confidence": "EXTRACTED", "source_file": "D:\\Padhai\\Style-Sync-AI\\context\\feature-specs\\23-redis-cache-rate-limiting.md", "source_location": "L206", "weight": 1.0}, {"source": "feature_specs_23_redis_cache_rate_limiting_weather_cache", "target": "feature_specs_23_redis_cache_rate_limiting_current_implementation_208", "relation": "contains", "confidence": "EXTRACTED", "source_file": "D:\\Padhai\\Style-Sync-AI\\context\\feature-specs\\23-redis-cache-rate-limiting.md", "source_location": "L208", "weight": 1.0}, {"source": "feature_specs_23_redis_cache_rate_limiting_weather_cache", "target": "feature_specs_23_redis_cache_rate_limiting_new_implementation_218", "relation": "contains", "confidence": "EXTRACTED", "source_file": "D:\\Padhai\\Style-Sync-AI\\context\\feature-specs\\23-redis-cache-rate-limiting.md", "source_location": "L218", "weight": 1.0}, {"source": "d_padhai_style_sync_ai_context_feature_specs_23_redis_cache_rate_limiting_md", "target": "feature_specs_23_redis_cache_rate_limiting_style_dna_cache_f1_preparation", "relation": "contains", "confidence": "EXTRACTED", "source_file": "D:\\Padhai\\Style-Sync-AI\\context\\feature-specs\\23-redis-cache-rate-limiting.md", "source_location": "L266", "weight": 1.0}, {"source": "d_padhai_style_sync_ai_context_feature_specs_23_redis_cache_rate_limiting_md", "target": "feature_specs_23_redis_cache_rate_limiting_capsule_audit_cache_f2_preparation", "relation": "contains", "confidence": "EXTRACTED", "source_file": "D:\\Padhai\\Style-Sync-AI\\context\\feature-specs\\23-redis-cache-rate-limiting.md", "source_location": "L299", "weight": 1.0}, {"source": "d_padhai_style_sync_ai_context_feature_specs_23_redis_cache_rate_limiting_md", "target": "feature_specs_23_redis_cache_rate_limiting_redis_key_namespace", "relation": "contains", "confidence": "EXTRACTED", "source_file": "D:\\Padhai\\Style-Sync-AI\\context\\feature-specs\\23-redis-cache-rate-limiting.md", "source_location": "L332", "weight": 1.0}, {"source": "d_padhai_style_sync_ai_context_feature_specs_23_redis_cache_rate_limiting_md", "target": "feature_specs_23_redis_cache_rate_limiting_database_changes", "relation": "contains", "confidence": "EXTRACTED", "source_file": "D:\\Padhai\\Style-Sync-AI\\context\\feature-specs\\23-redis-cache-rate-limiting.md", "source_location": "L346", "weight": 1.0}, {"source": "d_padhai_style_sync_ai_context_feature_specs_23_redis_cache_rate_limiting_md", "target": "feature_specs_23_redis_cache_rate_limiting_files_to_create", "relation": "contains", "confidence": "EXTRACTED", "source_file": "D:\\Padhai\\Style-Sync-AI\\context\\feature-specs\\23-redis-cache-rate-limiting.md", "source_location": "L352", "weight": 1.0}, {"source": "d_padhai_style_sync_ai_context_feature_specs_23_redis_cache_rate_limiting_md", "target": "feature_specs_23_redis_cache_rate_limiting_files_to_modify", "relation": "contains", "confidence": "EXTRACTED", "source_file": "D:\\Padhai\\Style-Sync-AI\\context\\feature-specs\\23-redis-cache-rate-limiting.md", "source_location": "L362", "weight": 1.0}, {"source": "d_padhai_style_sync_ai_context_feature_specs_23_redis_cache_rate_limiting_md", "target": "feature_specs_23_redis_cache_rate_limiting_constraints", "relation": "contains", "confidence": "EXTRACTED", "source_file": "D:\\Padhai\\Style-Sync-AI\\context\\feature-specs\\23-redis-cache-rate-limiting.md", "source_location": "L385", "weight": 1.0}, {"source": "d_padhai_style_sync_ai_context_feature_specs_23_redis_cache_rate_limiting_md", "target": "feature_specs_23_redis_cache_rate_limiting_check_when_done", "relation": "contains", "confidence": "EXTRACTED", "source_file": "D:\\Padhai\\Style-Sync-AI\\context\\feature-specs\\23-redis-cache-rate-limiting.md", "source_location": "L398", "weight": 1.0}], "input_tokens": 0, "output_tokens": 0}